[
    {
        "id": 1,
        "activeClass": "",
        "thumb": "fun-fact1.png",
        "delay": "100",
        "title": "Creative Vision",
        "end": "1"
    },
    {
        "id": 2,
        "activeClass": "",
        "thumb": "fun-fact2.png",
        "delay": "200",
        "title": "Smart Execution",
        "end": "2"
    },
    {
        "id": 3,
        "activeClass": "",
        "thumb": "fun-fact3.png",
        "delay": "400",
        "title": "Global Reach",
        "end": "3"
    },
    {
        "id": 4,
        "activeClass": "",
        "thumb": "fun-fact4.png",
        "delay": "600",
        "title": "Powerful Motion",
        "end": "4"
    }
]
